setup.py
Motebus/__init__.py
python_motebus.egg-info/PKG-INFO
python_motebus.egg-info/SOURCES.txt
python_motebus.egg-info/dependency_links.txt
python_motebus.egg-info/not-zip-safe
python_motebus.egg-info/top_level.txt