Metadata-Version: 1.0
Name: python-motebus
Version: 0.2.1
Summary: peer to peer communication protocol
Home-page: https://github.com/motebus/python-motebus
Author: YPCloud
Author-email: info@ypcloud.com
License: YPCloud
Platform: UNKNOWN
